README.rst
setup.cfg
setup.py
pbclient/__init__.py
pybossa_client.egg-info/PKG-INFO
pybossa_client.egg-info/SOURCES.txt
pybossa_client.egg-info/dependency_links.txt
pybossa_client.egg-info/requires.txt
pybossa_client.egg-info/top_level.txt
test/test_category.py
test/test_default.py
test/test_helpingmaterial.py
test/test_project.py
test/test_result.py
test/test_task.py
test/test_task_run.py