Metadata-Version: 1.1
Name: pybossa-client
Version: 2.0.0
Summary: pybossa-client is a tiny Python library makes it easy to work with PYBOSSA.
Home-page: https://github.com/Scifabric/pybossa-client
Author: Open Knowledge Foundation Labs
Author-email: teleyinex@gmail.com
License: MIT
Download-URL: https://github.com/Scifabric/pybossa-client/zipball/master
Platform: UNKNOWN
Classifier: Development Status :: 3 - Alpha
Classifier: Environment :: Console
Classifier: Intended Audience :: Developers
Classifier: License :: OSI Approved :: MIT License
Classifier: Operating System :: OS Independent
Classifier: Programming Language :: Python
Classifier: Topic :: Software Development :: Libraries :: Python Modules
